<?xml version="1.0" encoding="UTF-8"?>
<objects serializationModel="Studio.02.03.00">
	<object class="AudioFile" id="{08066b8a-9485-43f9-be50-96543d7e0474}">
		<property name="assetPath">
			<value>Voice/Al/2.wav</value>
		</property>
		<property name="frequencyInKHz">
			<value>48</value>
		</property>
		<property name="channelCount">
			<value>1</value>
		</property>
		<property name="length">
			<value>2.7208125000000001</value>
		</property>
		<relationship name="masterAssetFolder">
			<destination>{c7a5bce6-c66b-4a61-9eea-803fc4b8e9f0}</destination>
		</relationship>
	</object>
</objects>
